kinopoisk_unofficial/__init__.py
kinopoisk_unofficial/kinopoisk_api_client.py
kinopoisk_unofficial/client/__init__.py
kinopoisk_unofficial/client/api_client.py
kinopoisk_unofficial/client/films_api_client.py
kinopoisk_unofficial/client/http_client.py
kinopoisk_unofficial/client/http_method.py
kinopoisk_unofficial/client/persons_api_client.py
kinopoisk_unofficial/client/reviews_api_client.py
kinopoisk_unofficial/client/staff_api_client.py
kinopoisk_unofficial/client/exception/__init__.py
kinopoisk_unofficial/client/exception/bad_request.py
kinopoisk_unofficial/client/exception/not_found.py
kinopoisk_unofficial/client/exception/too_many_requests.py
kinopoisk_unofficial/client/exception/unauthorized.py
kinopoisk_unofficial/contract/__init__.py
kinopoisk_unofficial/contract/request.py
kinopoisk_unofficial/contract/response.py
kinopoisk_unofficial/model/__init__.py
kinopoisk_unofficial/model/box_office.py
kinopoisk_unofficial/model/company.py
kinopoisk_unofficial/model/country.py
kinopoisk_unofficial/model/digital_release.py
kinopoisk_unofficial/model/distribution.py
kinopoisk_unofficial/model/episode.py
kinopoisk_unofficial/model/fact.py
kinopoisk_unofficial/model/film.py
kinopoisk_unofficial/model/film_frame.py
kinopoisk_unofficial/model/film_sequels_and_prequels.py
kinopoisk_unofficial/model/film_video.py
kinopoisk_unofficial/model/filter_country.py
kinopoisk_unofficial/model/filter_genre.py
kinopoisk_unofficial/model/filter_order.py
kinopoisk_unofficial/model/found_film_by_filters.py
kinopoisk_unofficial/model/found_film_by_keyword.py
kinopoisk_unofficial/model/genre.py
kinopoisk_unofficial/model/image.py
kinopoisk_unofficial/model/person.py
kinopoisk_unofficial/model/person_film.py
kinopoisk_unofficial/model/premiere_film.py
kinopoisk_unofficial/model/related_film.py
kinopoisk_unofficial/model/review.py
kinopoisk_unofficial/model/season.py
kinopoisk_unofficial/model/spouse.py
kinopoisk_unofficial/model/staff.py
kinopoisk_unofficial/model/top_film.py
kinopoisk_api_unofficial_client-2.2.2.dist-info/LICENSE
kinopoisk_api_unofficial_client-2.2.2.dist-info/METADATA
kinopoisk_api_unofficial_client-2.2.2.dist-info/WHEEL
kinopoisk_api_unofficial_client-2.2.2.dist-info/top_level.txt
kinopoisk_api_unofficial_client-2.2.2.dist-info/RECORD
