Metadata-Version: 2.1
Name: kinopoisk-api-unofficial-client
Version: 2.2.2
Summary: API Client for the unofficial Kinopoisk api
Home-page: https://github.com/masterWeber/kinopoisk-api-unofficial-client
Author: Master Weber
Author-email: master.weber@outlook.com
Classifier: Programming Language :: Python :: 3.9
Classifier: License :: OSI Approved :: MIT License
Classifier: Operating System :: OS Independent
Requires-Python: >=3.9
License-File: LICENSE
Requires-Dist: requests (<=2.26.0)
Requires-Dist: apischema (==0.15.6)
